Metadata-Version: 2.1
Name: auto-files-identifier
Version: 0.0.3
Summary: Automatic File Identifier
Home-page: UNKNOWN
Author: Supratik Chatterjee
Author-email: supratikdevm96@gmail.com
License: MIT
Project-URL: Source, https://github.com/supratikchatterjee16/afi
Project-URL: Issues, https://github.com/supratikchatterjee16/afi/issues
Keywords: extensions signatures filehandling file identification
Platform: UNKNOWN
Classifier: Programming Language :: Python :: 3
Classifier: License :: OSI Approved :: MIT License
Classifier: Operating System :: OS Independent
License-File: LICENSE
